MANIFEST.in
README.md
setup.py
webim/__init__.py
webim/client.py
webim.egg-info/PKG-INFO
webim.egg-info/SOURCES.txt
webim.egg-info/dependency_links.txt
webim.egg-info/top_level.txt