Metadata-Version: 1.1
Name: webim
Version: 5.4.1
Summary: Python webim client for nextalk.im
Home-page: http://github.com/webim/webim-python
Author: Ery Lee
Author-email: ery.lee@gmail.com
License: BSD
Download-URL: http://github.com/webim/webim-python
Platform: UNKNOWN
Classifier: Development Status :: 4 - Beta
Classifier: Environment :: Web Environment
Classifier: Intended Audience :: Developers
Classifier: License :: OSI Approved :: BSD License
Classifier: Operating System :: OS Independent
Classifier: Programming Language :: Python
Classifier: Topic :: Internet
Classifier: Topic :: Software Development :: Libraries :: Python Modules
